json_schema_discovery/__init__.py
json_schema_discovery-1.3.2.dist-info/WHEEL
json_schema_discovery-1.3.2.dist-info/METADATA
json_schema_discovery-1.3.2.dist-info/RECORD
