Metadata-Version: 2.1
Name: json-schema-discovery
Version: 1.3.2
Summary: Database-agnostic JSON schema discovery
Author: Stepland
Author-email: Stepland@hotmail.fr
Requires-Python: >=3.7,<4.0
Classifier: Programming Language :: Python :: 3
Classifier: Programming Language :: Python :: 3.7
Requires-Dist: tabulate (>=0.8.3,<0.9.0)
